{"chunk_definitions":[{"row":13,"row_count":1,"visible":true,"expansion_state":0,"options":{"engine":"r","label":"unnamed-chunk-43","dev":"png"},"document_id":"F63BC046","chunk_id":"cyap6g63ifq4k","chunk_label":"unnamed-chunk-1"},{"row":43,"row_count":1,"visible":true,"expansion_state":0,"options":{"engine":"r","label":"unnamed-chunk-14","dev":"png"},"document_id":"F63BC046","chunk_id":"ca3dv41i2qr6i","chunk_label":"unnamed-chunk-2"},{"row":44,"row_count":1,"visible":true,"expansion_state":0,"options":{"engine":"r","label":"unnamed-chunk-61","dev":"png"},"document_id":"F63BC046","chunk_id":"cjowswakikrlk","chunk_label":"unnamed-chunk-2"},{"row":50,"row_count":1,"visible":true,"expansion_state":0,"options":{"engine":"r","label":"unnamed-chunk-25","dev":"png"},"document_id":"F63BC046","chunk_id":"c876ujlhhv2na","chunk_label":"unnamed-chunk-3"},{"row":66,"row_count":1,"visible":true,"expansion_state":0,"options":{"engine":"r","label":"unnamed-chunk-56","dev":"png"},"document_id":"F63BC046","chunk_id":"c88b8qas6s8at","chunk_label":"unnamed-chunk-4"},{"row":79,"row_count":1,"visible":true,"expansion_state":0,"options":{"engine":"r","label":"unnamed-chunk-57","dev":"png"},"document_id":"F63BC046","chunk_id":"cc91x6466qqvz","chunk_label":"unnamed-chunk-5"},{"row":93,"row_count":1,"visible":true,"expansion_state":0,"options":{"engine":"r","label":"unnamed-chunk-58","dev":"png"},"document_id":"F63BC046","chunk_id":"ca97ojtiewj0y","chunk_label":"unnamed-chunk-6"},{"row":101,"row_count":1,"visible":true,"expansion_state":0,"options":{"engine":"r","label":"unnamed-chunk-46","dev":"png"},"document_id":"F63BC046","chunk_id":"cc6m5w0ygtasv","chunk_label":"unnamed-chunk-7"},{"row":109,"row_count":1,"visible":true,"expansion_state":0,"options":{"engine":"r","label":"unnamed-chunk-68","dev":"png"},"document_id":"F63BC046","chunk_id":"c1h3fbb9ma931","chunk_label":"unnamed-chunk-8"},{"row":116,"row_count":1,"visible":true,"expansion_state":0,"options":{"engine":"r","label":"unnamed-chunk-69","dev":"png"},"document_id":"F63BC046","chunk_id":"c4hcczi8u0jv8","chunk_label":"unnamed-chunk-9"},{"row":125,"row_count":1,"visible":true,"expansion_state":0,"options":{"engine":"r","label":"unnamed-chunk-72","dev":"png"},"document_id":"F63BC046","chunk_id":"c8i9o44ef8w0y","chunk_label":"unnamed-chunk-10"}],"doc_write_time":1716398286,"chunk_rendered_width":700}